django_domain/__init__.py
django_domain-0.1.0a0.dist-info/METADATA
django_domain-0.1.0a0.dist-info/WHEEL
django_domain-0.1.0a0.dist-info/RECORD
