Metadata-Version: 2.3
Name: django-domain
Version: 0.1.0a0
Summary: In Development - Please come back later.
Author: Stacy Noland
Author-email: 46572585+stacynoland@users.noreply.github.com
Requires-Python: >=3.13
Classifier: Programming Language :: Python :: 3
Classifier: Programming Language :: Python :: 3.13
